{
    "info": {
        "name": "School Chatbot API Collection",
        "description": "Complete API testing collection for School Attendance Chatbot with hybrid intelligence",
        "schema": "https://schema.getpostman.com/json/collection/v2.1.0/collection.json"
    },
    "variable": [
        {
            "key": "baseUrl",
            "value": "http://schoolchatbot-213277610.us-east-1.elb.amazonaws.com",
            "type": "string"
        },
        {
            "key": "apiKey",
            "value": "sk-school-api-key",
            "type": "string"
        }
    ],
    "item": [
        {
            "name": "Health Check",
            "request": {
                "method": "GET",
                "header": [],
                "url": {
                    "raw": "{{baseUrl}}/health",
                    "host": ["{{baseUrl}}"],
                    "path": ["health"]
                }
            }
        },
        {
            "name": "API Information",
            "request": {
                "method": "GET",
                "header": [],
                "url": {
                    "raw": "{{baseUrl}}/api/info",
                    "host": ["{{baseUrl}}"],
                    "path": ["api", "info"]
                }
            }
        },
        {
            "name": "Chat - Attendance Query",
            "request": {
                "method": "POST",
                "header": [
                    {
                        "key": "Authorization",
                        "value": "Bearer {{apiKey}}",
                        "type": "text"
                    },
                    {
                        "key": "Content-Type",
                        "value": "application/json",
                        "type": "text"
                    }
                ],
                "body": {
                    "mode": "raw",
                    "raw": "{\n    \"message\": \"What is John's attendance rate this month?\"\n}"
                },
                "url": {
                    "raw": "{{baseUrl}}/api/chat",
                    "host": ["{{baseUrl}}"],
                    "path": ["api", "chat"]
                }
            }
        },
        {
            "name": "Chat - News Query (India)",
            "request": {
                "method": "POST",
                "header": [
                    {
                        "key": "Authorization",
                        "value": "Bearer {{apiKey}}",
                        "type": "text"
                    },
                    {
                        "key": "Content-Type",
                        "value": "application/json",
                        "type": "text"
                    }
                ],
                "body": {
                    "mode": "raw",
                    "raw": "{\n    \"message\": \"Latest news in Chennai\"\n}"
                },
                "url": {
                    "raw": "{{baseUrl}}/api/chat",
                    "host": ["{{baseUrl}}"],
                    "path": ["api", "chat"]
                }
            }
        },
        {
            "name": "Chat - General Knowledge",
            "request": {
                "method": "POST",
                "header": [
                    {
                        "key": "Authorization",
                        "value": "Bearer {{apiKey}}",
                        "type": "text"
                    },
                    {
                        "key": "Content-Type",
                        "value": "application/json",
                        "type": "text"
                    }
                ],
                "body": {
                    "mode": "raw",
                    "raw": "{\n    \"message\": \"What is the capital of France?\"\n}"
                },
                "url": {
                    "raw": "{{baseUrl}}/api/chat",
                    "host": ["{{baseUrl}}"],
                    "path": ["api", "chat"]
                }
            }
        },
        {
            "name": "Get Students List",
            "request": {
                "method": "GET",
                "header": [
                    {
                        "key": "Authorization",
                        "value": "Bearer {{apiKey}}",
                        "type": "text"
                    }
                ],
                "url": {
                    "raw": "{{baseUrl}}/api/students",
                    "host": ["{{baseUrl}}"],
                    "path": ["api", "students"]
                }
            }
        },
        {
            "name": "Get News (US)",
            "request": {
                "method": "GET",
                "header": [
                    {
                        "key": "Authorization",
                        "value": "Bearer {{apiKey}}",
                        "type": "text"
                    }
                ],
                "url": {
                    "raw": "{{baseUrl}}/api/news",
                    "host": ["{{baseUrl}}"],
                    "path": ["api", "news"]
                }
            }
        },
        {
            "name": "Get News (India)",
            "request": {
                "method": "GET",
                "header": [
                    {
                        "key": "Authorization",
                        "value": "Bearer {{apiKey}}",
                        "type": "text"
                    }
                ],
                "url": {
                    "raw": "{{baseUrl}}/api/news?location=chennai",
                    "host": ["{{baseUrl}}"],
                    "path": ["api", "news"],
                    "query": [
                        {
                            "key": "location",
                            "value": "chennai"
                        }
                    ]
                }
            }
        },
        {
            "name": "Update Attendance",
            "request": {
                "method": "PUT",
                "header": [
                    {
                        "key": "Authorization",
                        "value": "Bearer {{apiKey}}",
                        "type": "text"
                    },
                    {
                        "key": "Content-Type",
                        "value": "application/json",
                        "type": "text"
                    }
                ],
                "body": {
                    "mode": "raw",
                    "raw": "{\n    \"student_name\": \"John Smith\",\n    \"date\": \"2024-10-12\",\n    \"status\": \"present\",\n    \"grade\": \"10th\"\n}"
                },
                "url": {
                    "raw": "{{baseUrl}}/api/attendance",
                    "host": ["{{baseUrl}}"],
                    "path": ["api", "attendance"]
                }
            }
        }
    ]
}